LICENSE.rst
pytest_isort/__init__.py
pytest_isort-4.0.0.dist-info/LICENSE.rst
pytest_isort-4.0.0.dist-info/METADATA
pytest_isort-4.0.0.dist-info/WHEEL
pytest_isort-4.0.0.dist-info/entry_points.txt
pytest_isort-4.0.0.dist-info/RECORD
