Metadata-Version: 2.1
Name: pytest-isort
Version: 4.0.0
Summary: py.test plugin to check import ordering using isort
Home-page: https://github.com/stephrdev/pytest-isort
License: MIT
Author: Stephan Jaekel
Author-email: steph@rdev.info
Requires-Python: >=3.8,<4
Classifier: Development Status :: 5 - Production/Stable
Classifier: Framework :: Pytest
Classifier: Intended Audience :: Developers
Classifier: License :: OSI Approved :: MIT License
Classifier: Operating System :: OS Independent
Classifier: Programming Language :: Python
Classifier: Programming Language :: Python :: 3
Classifier: Programming Language :: Python :: 3.8
Classifier: Programming Language :: Python :: 3.9
Classifier: Programming Language :: Python :: 3.10
Classifier: Programming Language :: Python :: 3.11
Classifier: Programming Language :: Python :: 3.12
Classifier: Topic :: Software Development :: Testing
Requires-Dist: isort (>=4.0)
Requires-Dist: pytest (>=5.0)
Project-URL: Repository, https://github.com/stephrdev/pytest-isort
